{
  "generated_at": "2026-03-25T23:14:15.072Z",
  "project_url": "https://krnabtkugfzfinwvfuzm.supabase.co",
  "tables": {
    "leads": [
      {
        "id": "02d652f6-4d2c-42bb-9657-0c4c7c24e20e",
        "visitor_id": "1482c50a-b8e7-44ed-a00a-8c660f95424f",
        "fingerprint_hash": "fp_hash_test_123",
        "modelo_id": "MODEL_ID_PLACEHOLDER",
        "utm_source": "instagram",
        "idioma": "es",
        "dispositivo": "mobile",
        "user_agent": "proxy-smoke-test",
        "ip_hash": "17413cbe0a5db653145c162ba8570298861134c7a0ffda9f2f6d5826fd397275",
        "of_activo": false,
        "telegram_activo": false,
        "created_at": "2026-03-25T16:15:35.367164+00:00",
        "updated_at": "2026-03-25T16:15:35.928779+00:00",
        "invite_link": null,
        "invite_link_created_at": null,
        "last_bot_action": null,
        "active_flow": null,
        "winback_sent": false,
        "telegram_user_id": null
      },
      {
        "id": "a671f0a9-11ab-4c0d-a5a3-9f3d204259ac",
        "visitor_id": "6d484e1d-b2f0-48e2-8b90-b401f7beb282",
        "fingerprint_hash": "fp_hash_test_123",
        "modelo_id": "MODEL_ID_PLACEHOLDER",
        "utm_source": "instagram",
        "idioma": "es",
        "dispositivo": "mobile",
        "user_agent": "proxy-smoke-test",
        "ip_hash": "a5108cf2614b7f866d61cef232fcc47159ff47556ec04960a8983874ba872574",
        "of_activo": false,
        "telegram_activo": false,
        "created_at": "2026-03-25T16:15:44.053011+00:00",
        "updated_at": "2026-03-25T16:15:44.639345+00:00",
        "invite_link": null,
        "invite_link_created_at": null,
        "last_bot_action": null,
        "active_flow": null,
        "winback_sent": false,
        "telegram_user_id": null
      },
      {
        "id": "e741056c-356f-4f62-8f5b-68f5d996fa3d",
        "visitor_id": "08126fc3-f423-42af-ab2a-8fc957dddfbf",
        "fingerprint_hash": "fp_hash_test_123",
        "modelo_id": "MODEL_ID_PLACEHOLDER",
        "utm_source": "instagram",
        "idioma": "es",
        "dispositivo": "mobile",
        "user_agent": "proxy-smoke-test",
        "ip_hash": "59f164b77f2365af9870f83c939de29eb74445c03c26e69ae7b67a9a377f6afa",
        "of_activo": false,
        "telegram_activo": false,
        "created_at": "2026-03-25T16:16:35.375286+00:00",
        "updated_at": "2026-03-25T16:16:35.898718+00:00",
        "invite_link": null,
        "invite_link_created_at": null,
        "last_bot_action": null,
        "active_flow": null,
        "winback_sent": false,
        "telegram_user_id": null
      },
      {
        "id": "957eab06-2055-4327-aded-273b67585881",
        "visitor_id": "c58f3152-1d68-4f0f-a65f-76959ee31f4f",
        "fingerprint_hash": "fp_hash_test_123",
        "modelo_id": "MODEL_ID_PLACEHOLDER",
        "utm_source": "instagram",
        "idioma": "es",
        "dispositivo": "mobile",
        "user_agent": "proxy-smoke-test",
        "ip_hash": "af52c012cfc02ff0279e09f3dd14dd3f8e240ac8caadb666a7d9fa7752a088d6",
        "of_activo": false,
        "telegram_activo": false,
        "created_at": "2026-03-25T16:17:04.158672+00:00",
        "updated_at": "2026-03-25T16:17:04.158672+00:00",
        "invite_link": null,
        "invite_link_created_at": null,
        "last_bot_action": null,
        "active_flow": null,
        "winback_sent": false,
        "telegram_user_id": null
      },
      {
        "id": "611518bc-e671-4a31-b3f5-7318920f608c",
        "visitor_id": "54a2457a-9790-4cf1-ac8d-304f0d1d453e",
        "fingerprint_hash": "fp_666ee08a3d694e8fb5cf21d6d4f13fee",
        "modelo_id": "MODEL_ID_PLACEHOLDER",
        "utm_source": "instagram",
        "idioma": "es",
        "dispositivo": "mobile",
        "user_agent": "e2e-script",
        "ip_hash": "d363faada9dbe098a0d0e77eb13d4bb9a41ba75fb8ff5e4794d4b74784b42968",
        "of_activo": false,
        "telegram_activo": false,
        "created_at": "2026-03-25T16:57:51.362812+00:00",
        "updated_at": "2026-03-25T16:57:52.058999+00:00",
        "invite_link": null,
        "invite_link_created_at": null,
        "last_bot_action": null,
        "active_flow": null,
        "winback_sent": false,
        "telegram_user_id": null
      },
      {
        "id": "a71f732d-4b28-4266-8c87-0576e9bb1f92",
        "visitor_id": "dfd5b49a-0e34-4680-983e-4e6d072223dd",
        "fingerprint_hash": "fp_2d72023bb2e94ba4a3ef38ab407bb936",
        "modelo_id": "MODEL_ID_PLACEHOLDER",
        "utm_source": "instagram",
        "idioma": "es",
        "dispositivo": "mobile",
        "user_agent": "e2e-script",
        "ip_hash": "d52a50c551d2e6b269d09beb688972fe621a22939e9135ec1f0ade2321014422",
        "of_activo": false,
        "telegram_activo": false,
        "created_at": "2026-03-25T16:58:54.406314+00:00",
        "updated_at": "2026-03-25T16:58:54.914154+00:00",
        "invite_link": null,
        "invite_link_created_at": null,
        "last_bot_action": null,
        "active_flow": null,
        "winback_sent": false,
        "telegram_user_id": null
      },
      {
        "id": "144110b5-7e43-4079-924e-606ff04d78e2",
        "visitor_id": "test-batch-1774477751727-f1-user",
        "fingerprint_hash": "fp_test-batch-1774477751727_deviceA",
        "modelo_id": "MODEL_ID_PLACEHOLDER",
        "utm_source": "tiktok",
        "idioma": "es",
        "dispositivo": "mobile",
        "user_agent": "f1-test",
        "ip_hash": "d711f5b5b95a85bf7140eeae050bd0e94a508125aad1cb5e03a5c81e6cbb57c6",
        "of_activo": false,
        "telegram_activo": false,
        "created_at": "2026-03-25T22:29:13.463296+00:00",
        "updated_at": "2026-03-25T22:29:14.715099+00:00",
        "invite_link": null,
        "invite_link_created_at": null,
        "last_bot_action": null,
        "active_flow": null,
        "winback_sent": false,
        "telegram_user_id": null
      },
      {
        "id": "251e99df-2a57-4a18-b7f5-84fa5365b816",
        "visitor_id": "91c31bf1-c7ff-4d66-a1ca-c2f574947f3a",
        "fingerprint_hash": "dup_3c251b8cb1324009b0a16951c660d451",
        "modelo_id": "MODEL_ID_PLACEHOLDER",
        "utm_source": "edge",
        "idioma": "es",
        "dispositivo": "mobile",
        "user_agent": "audit-edge",
        "ip_hash": "2ed32fb15d73e319515d0279b802af54e3de1c272f6aed3deecc34eb9407bcd3",
        "of_activo": false,
        "telegram_activo": false,
        "created_at": "2026-03-25T17:02:25.247232+00:00",
        "updated_at": "2026-03-25T17:02:25.74672+00:00",
        "invite_link": null,
        "invite_link_created_at": null,
        "last_bot_action": null,
        "active_flow": null,
        "winback_sent": false,
        "telegram_user_id": null
      },
      {
        "id": "cc89d904-d40f-4e05-bd87-6cad98d9e6d8",
        "visitor_id": "edge-invite-1774458146134",
        "fingerprint_hash": null,
        "modelo_id": "MODEL_ID_PLACEHOLDER",
        "utm_source": null,
        "idioma": null,
        "dispositivo": null,
        "user_agent": null,
        "ip_hash": null,
        "of_activo": false,
        "telegram_activo": false,
        "created_at": "2026-03-25T17:02:26.870852+00:00",
        "updated_at": "2026-03-25T17:02:26.870852+00:00",
        "invite_link": "https://t.me/+Xu_-s88DwyxjYWQ0",
        "invite_link_created_at": "2026-03-25T17:02:26.831+00:00",
        "last_bot_action": null,
        "active_flow": null,
        "winback_sent": false,
        "telegram_user_id": null
      },
      {
        "id": "3506bf0f-b328-40f8-9915-48524a980944",
        "visitor_id": "0413bc0b-b98e-450d-abed-8a2f356f90b1",
        "fingerprint_hash": "fp_conc_bc264b45d570474880ef8d0637787259",
        "modelo_id": "MODEL_ID_PLACEHOLDER",
        "utm_source": "stress",
        "idioma": "es",
        "dispositivo": "mobile",
        "user_agent": "stress-concurrency",
        "ip_hash": "d3f642e4b75d1d921646530f94ab3f5da9fdf61155aa1bfe74430f35772e34dd",
        "of_activo": false,
        "telegram_activo": false,
        "created_at": "2026-03-25T16:58:11.507306+00:00",
        "updated_at": "2026-03-25T16:58:11.764492+00:00",
        "invite_link": null,
        "invite_link_created_at": null,
        "last_bot_action": null,
        "active_flow": null,
        "winback_sent": false,
        "telegram_user_id": null
      },
      {
        "id": "dbf08c2c-a93f-482b-9240-9b9d5c489be9",
        "visitor_id": "983222f1-06bc-470c-ba9a-3a5ce2142d44",
        "fingerprint_hash": "dup_6f62ebbf1cb147ecb35bdc4a6b9087d4",
        "modelo_id": "MODEL_ID_PLACEHOLDER",
        "utm_source": "edge",
        "idioma": "es",
        "dispositivo": "mobile",
        "user_agent": "audit-edge",
        "ip_hash": "801b3f94fa36b0531c5d457e797988b1ddb8ddc9f73dd78af205f8a7f244c782",
        "of_activo": false,
        "telegram_activo": false,
        "created_at": "2026-03-25T17:03:12.369078+00:00",
        "updated_at": "2026-03-25T17:03:12.829741+00:00",
        "invite_link": null,
        "invite_link_created_at": null,
        "last_bot_action": null,
        "active_flow": null,
        "winback_sent": false,
        "telegram_user_id": null
      },
      {
        "id": "368768b2-a2f8-4094-bddf-4da7940013b9",
        "visitor_id": "edge-invite-1774458193170",
        "fingerprint_hash": null,
        "modelo_id": "MODEL_ID_PLACEHOLDER",
        "utm_source": null,
        "idioma": null,
        "dispositivo": null,
        "user_agent": null,
        "ip_hash": null,
        "of_activo": false,
        "telegram_activo": false,
        "created_at": "2026-03-25T17:03:13.913672+00:00",
        "updated_at": "2026-03-25T17:03:13.913672+00:00",
        "invite_link": "https://t.me/+vDMPF70oBYU4YWQ0",
        "invite_link_created_at": "2026-03-25T17:03:13.86+00:00",
        "last_bot_action": null,
        "active_flow": null,
        "winback_sent": false,
        "telegram_user_id": null
      },
      {
        "id": "71ec97ca-fa25-4540-a54b-3d9aa0edf353",
        "visitor_id": "stress-1774457938570",
        "fingerprint_hash": "fp_stress_393304cecc784f219fc20ac7c9ae1491",
        "modelo_id": "MODEL_ID_PLACEHOLDER",
        "utm_source": "stress",
        "idioma": "es",
        "dispositivo": "mobile",
        "user_agent": "stress-bulk",
        "ip_hash": "796a85b3f9d71f31fc369a560cae9e9201879f78947a97ed157ab4c4aba637e2",
        "of_activo": false,
        "telegram_activo": false,
        "created_at": "2026-03-25T16:58:59.176126+00:00",
        "updated_at": "2026-03-25T16:59:11.185576+00:00",
        "invite_link": null,
        "invite_link_created_at": null,
        "last_bot_action": null,
        "active_flow": null,
        "winback_sent": false,
        "telegram_user_id": null
      },
      {
        "id": "6b1a1b69-44a6-4b7f-b68d-012ed33c3ab3",
        "visitor_id": "743b6c10-9d53-42b6-8917-75304e25b425",
        "fingerprint_hash": "fp_concurrency_d8770b38b84f41c689d8aef54f9a573a",
        "modelo_id": "MODEL_ID_PLACEHOLDER",
        "utm_source": "stress",
        "idioma": "es",
        "dispositivo": "mobile",
        "user_agent": "stress-concurrency",
        "ip_hash": "b72d7b8050592ad8fa43fd5dad3d1d0596006698d3ee083b2ca5ecc7fd80c6a1",
        "of_activo": false,
        "telegram_activo": false,
        "created_at": "2026-03-25T16:58:58.230639+00:00",
        "updated_at": "2026-03-25T16:58:58.627466+00:00",
        "invite_link": null,
        "invite_link_created_at": null,
        "last_bot_action": null,
        "active_flow": null,
        "winback_sent": false,
        "telegram_user_id": null
      },
      {
        "id": "e4e83800-3fcb-4172-8ace-392fcb98a6e9",
        "visitor_id": "stress-1774457902851",
        "fingerprint_hash": "fp_stress_484e376783404763ac3f4a85f78cdb78",
        "modelo_id": "MODEL_ID_PLACEHOLDER",
        "utm_source": "stress",
        "idioma": "es",
        "dispositivo": "mobile",
        "user_agent": "stress-bulk",
        "ip_hash": "cc05c5c89ad1b714ff9ac6e4b1dbec5312ff782ab6cc1dbeafdf6fc22da2156b",
        "of_activo": false,
        "telegram_activo": false,
        "created_at": "2026-03-25T16:58:23.548757+00:00",
        "updated_at": "2026-03-25T16:58:33.988667+00:00",
        "invite_link": null,
        "invite_link_created_at": null,
        "last_bot_action": null,
        "active_flow": null,
        "winback_sent": false,
        "telegram_user_id": null
      },
      {
        "id": "0ff51518-1936-41ec-8a10-c1e547fd36a1",
        "visitor_id": "24bcbb59-d22b-4b26-820f-03140c22c12c",
        "fingerprint_hash": "smoke_fp_62508e2efdcf44879ae80b982deb0242",
        "modelo_id": "MODEL_ID_PLACEHOLDER",
        "utm_source": "smoke",
        "idioma": "es",
        "dispositivo": "mobile",
        "user_agent": "smoke-daily",
        "ip_hash": "cb6f52903d44cdc3d80db5ff00aa8aeb99b0d099d3f04f1fe7a44702d0e4e51c",
        "of_activo": false,
        "telegram_activo": false,
        "created_at": "2026-03-25T18:04:06.267291+00:00",
        "updated_at": "2026-03-25T18:04:07.955926+00:00",
        "invite_link": "https://t.me/+LY7xWVbYaLZhMWVk",
        "invite_link_created_at": "2026-03-25T18:04:06.177+00:00",
        "last_bot_action": null,
        "active_flow": null,
        "winback_sent": false,
        "telegram_user_id": null
      },
      {
        "id": "ab473d92-c40a-48c4-876c-e491477df096",
        "visitor_id": "feec137e-5b4d-4247-acd7-7331fda6de2c",
        "fingerprint_hash": "audit_fp_d6552ea580504fc59474db2aab0ce412",
        "modelo_id": "MODEL_ID_PLACEHOLDER",
        "utm_source": "instagram",
        "idioma": "es",
        "dispositivo": "mobile",
        "user_agent": "audit-script",
        "ip_hash": "2545ac2224deb1c06d0c25dc521275e026b04ee6a9ab5c9da16faedd364c9647",
        "of_activo": false,
        "telegram_activo": true,
        "created_at": "2026-03-25T17:02:21.795063+00:00",
        "updated_at": "2026-03-25T17:02:23.816293+00:00",
        "invite_link": "https://t.me/+HMFprTCITFE2ZGE0",
        "invite_link_created_at": "2026-03-25T17:02:21.67+00:00",
        "last_bot_action": null,
        "active_flow": null,
        "winback_sent": false,
        "telegram_user_id": null
      },
      {
        "id": "0cba877b-abcb-4b42-a952-ac4bc37e6840",
        "visitor_id": "9aeec2a6-45be-4dba-89e8-9202926a2fc0",
        "fingerprint_hash": "audit_fp_f2163754d2ff44e88d531543d66755c2",
        "modelo_id": "MODEL_ID_PLACEHOLDER",
        "utm_source": "instagram",
        "idioma": "es",
        "dispositivo": "mobile",
        "user_agent": "audit-script",
        "ip_hash": "a6917ecf8d4eac40a1adde22c763d0625b39569c6c1fadd1a5b3717ebcc5d9e1",
        "of_activo": false,
        "telegram_activo": true,
        "created_at": "2026-03-25T17:03:09.197088+00:00",
        "updated_at": "2026-03-25T18:18:07.861219+00:00",
        "invite_link": "https://t.me/+4ENDiLQCszs5YmM0",
        "invite_link_created_at": "2026-03-25T17:03:09.128+00:00",
        "last_bot_action": null,
        "active_flow": null,
        "winback_sent": false,
        "telegram_user_id": "777001"
      },
      {
        "id": "ec25c057-5e60-4279-b146-6a70f5c64de2",
        "visitor_id": "qa_detector_1774463381988",
        "fingerprint_hash": null,
        "modelo_id": "MODEL_ID_PLACEHOLDER",
        "utm_source": "direct",
        "idioma": "es",
        "dispositivo": "mobile",
        "user_agent": null,
        "ip_hash": null,
        "of_activo": false,
        "telegram_activo": true,
        "created_at": "2026-03-25T18:29:42.678531+00:00",
        "updated_at": "2026-03-25T18:29:41.989+00:00",
        "invite_link": null,
        "invite_link_created_at": null,
        "last_bot_action": null,
        "active_flow": null,
        "winback_sent": false,
        "telegram_user_id": "777001"
      },
      {
        "id": "242a53c9-dbea-4e3e-8387-d327cde3ee14",
        "visitor_id": "test-batch-1774477751727-f2-invite",
        "fingerprint_hash": null,
        "modelo_id": "MODEL_ID_PLACEHOLDER",
        "utm_source": null,
        "idioma": null,
        "dispositivo": null,
        "user_agent": null,
        "ip_hash": null,
        "of_activo": false,
        "telegram_activo": true,
        "created_at": "2026-03-25T22:29:16.547791+00:00",
        "updated_at": "2026-03-25T22:29:17.954941+00:00",
        "invite_link": "https://t.me/+yjj1LeRSMj41MTM0",
        "invite_link_created_at": "2026-03-25T22:29:16.489+00:00",
        "last_bot_action": null,
        "active_flow": null,
        "winback_sent": false,
        "telegram_user_id": "999001"
      },
      {
        "id": "33d50219-99e2-4bdb-a93c-f888a7df4539",
        "visitor_id": "qa_winback_1774463381988",
        "fingerprint_hash": null,
        "modelo_id": "MODEL_ID_PLACEHOLDER",
        "utm_source": "instagram",
        "idioma": "es",
        "dispositivo": "mobile",
        "user_agent": null,
        "ip_hash": null,
        "of_activo": false,
        "telegram_activo": true,
        "created_at": "2026-03-25T18:29:42.678531+00:00",
        "updated_at": "2026-03-25T21:15:33.973728+00:00",
        "invite_link": null,
        "invite_link_created_at": null,
        "last_bot_action": "2026-03-25T21:15:33.618+00:00",
        "active_flow": "3",
        "winback_sent": true,
        "telegram_user_id": "777001"
      },
      {
        "id": "02626bb6-ceb7-47ad-b11e-8494dbc521ce",
        "visitor_id": "test-f25-final-1774477992089",
        "fingerprint_hash": "fp_test-f25-final-1774477992089",
        "modelo_id": "MODEL_ID_PLACEHOLDER",
        "utm_source": "reddit",
        "idioma": "es",
        "dispositivo": "mobile",
        "user_agent": "f25-final",
        "ip_hash": "13cc5de3451cf6217af4bfed8beb2fee433740127a24832d01b9587844e35d8c",
        "of_activo": false,
        "telegram_activo": true,
        "created_at": "2026-03-25T22:33:14.244792+00:00",
        "updated_at": "2026-03-25T22:35:29.133086+00:00",
        "invite_link": "https://t.me/+Ifx03DjAWjNjNjJk",
        "invite_link_created_at": "2026-03-25T22:33:14.164+00:00",
        "last_bot_action": "2026-03-25T22:35:28.76+00:00",
        "active_flow": "3",
        "winback_sent": false,
        "telegram_user_id": "999777"
      },
      {
        "id": "acf9ef2f-37bf-4a58-8315-d62eb46255a8",
        "visitor_id": "test-batch-1774477751727-f25",
        "fingerprint_hash": "fp_test-batch-1774477751727_f25",
        "modelo_id": "MODEL_ID_PLACEHOLDER",
        "utm_source": "reddit",
        "idioma": "es",
        "dispositivo": "mobile",
        "user_agent": "f25-test",
        "ip_hash": "baf4896a1e0b101e4656ce15dc3dfba5e1834edb9f64143375304d38e71571ab",
        "of_activo": false,
        "telegram_activo": true,
        "created_at": "2026-03-25T22:29:19.565177+00:00",
        "updated_at": "2026-03-25T22:29:20.980419+00:00",
        "invite_link": "https://t.me/+DMFXf141KwVmNmU0",
        "invite_link_created_at": "2026-03-25T22:29:19.523+00:00",
        "last_bot_action": null,
        "active_flow": null,
        "winback_sent": false,
        "telegram_user_id": "999555"
      },
      {
        "id": "ffcfbfb1-82f8-4034-b888-7d715b7f4e20",
        "visitor_id": "488bb783-7c28-442b-a508-5be8db15733a",
        "fingerprint_hash": "smoke_fp_53ff84257409458d9309c7cd39508da0",
        "modelo_id": "MODEL_ID_PLACEHOLDER",
        "utm_source": "smoke",
        "idioma": "es",
        "dispositivo": "mobile",
        "user_agent": "smoke-daily",
        "ip_hash": "63446c7a953654392cc27fbb9c54b0bef6897171b4b4e896b6cc8f7269bbadd6",
        "of_activo": false,
        "telegram_activo": false,
        "created_at": "2026-03-25T22:38:57.091377+00:00",
        "updated_at": "2026-03-25T22:38:58.278034+00:00",
        "invite_link": "https://t.me/+Gosi8mOHJ9djNWM0",
        "invite_link_created_at": "2026-03-25T22:38:57.05+00:00",
        "last_bot_action": null,
        "active_flow": null,
        "winback_sent": false,
        "telegram_user_id": null
      },
      {
        "id": "95bf0759-ae5d-4a05-b6ed-88175141c2da",
        "visitor_id": "e34085df-6b9f-401c-8513-d601ff85ecc3",
        "fingerprint_hash": "smoke_fp_984f5a982ef64a03a08c2a26a57bd574",
        "modelo_id": "MODEL_ID_PLACEHOLDER",
        "utm_source": "smoke",
        "idioma": "es",
        "dispositivo": "mobile",
        "user_agent": "smoke-daily",
        "ip_hash": "46bdf85cdc407961218ebfd899ebd028b66d513b2d5823bcbb4adf9967db6fa7",
        "of_activo": false,
        "telegram_activo": false,
        "created_at": "2026-03-25T22:45:02.887321+00:00",
        "updated_at": "2026-03-25T22:45:04.217081+00:00",
        "invite_link": "https://t.me/+flYqdZu5Le03ZjFk",
        "invite_link_created_at": "2026-03-25T22:45:02.844+00:00",
        "last_bot_action": null,
        "active_flow": null,
        "winback_sent": false,
        "telegram_user_id": null
      },
      {
        "id": "613b580b-a9fa-43d3-bc88-143edb82cb9c",
        "visitor_id": "test-f25-final-1774478688926",
        "fingerprint_hash": "fp_test-f25-final-1774478688926",
        "modelo_id": "MODEL_ID_PLACEHOLDER",
        "utm_source": "reddit",
        "idioma": "es",
        "dispositivo": "mobile",
        "user_agent": "f25-final",
        "ip_hash": "2f830cddd3d74d4edaa5988b8c0605a0c860aac5b5aec35cad768887ccd23ebf",
        "of_activo": false,
        "telegram_activo": true,
        "created_at": "2026-03-25T22:44:50.571268+00:00",
        "updated_at": "2026-03-25T22:45:28.704171+00:00",
        "invite_link": "https://t.me/+QpNp39misuZjNjI0",
        "invite_link_created_at": "2026-03-25T22:44:50.537+00:00",
        "last_bot_action": "2026-03-25T22:45:28.423+00:00",
        "active_flow": "3",
        "winback_sent": false,
        "telegram_user_id": "999777"
      },
      {
        "id": "0699cbb3-52c6-4f86-b361-27dd8533c073",
        "visitor_id": "test-batch-1774478704617-f1-user",
        "fingerprint_hash": "fp_test-batch-1774478704617_deviceA",
        "modelo_id": "MODEL_ID_PLACEHOLDER",
        "utm_source": "tiktok",
        "idioma": "es",
        "dispositivo": "mobile",
        "user_agent": "f1-test",
        "ip_hash": "796a85b3f9d71f31fc369a560cae9e9201879f78947a97ed157ab4c4aba637e2",
        "of_activo": false,
        "telegram_activo": false,
        "created_at": "2026-03-25T22:45:05.842054+00:00",
        "updated_at": "2026-03-25T22:45:06.987415+00:00",
        "invite_link": null,
        "invite_link_created_at": null,
        "last_bot_action": null,
        "active_flow": null,
        "winback_sent": false,
        "telegram_user_id": null
      },
      {
        "id": "4bbc9779-03ef-4cc2-99bf-fd3bc07d2ccc",
        "visitor_id": "856a3c5a-5870-4a0c-a417-a693e52e675f",
        "fingerprint_hash": "smoke_fp_5422491691144d38ad40bc960a2dd1b9",
        "modelo_id": "MODEL_ID_PLACEHOLDER",
        "utm_source": "smoke",
        "idioma": "es",
        "dispositivo": "mobile",
        "user_agent": "smoke-daily",
        "ip_hash": "9ed9cdcccf4f3c88207618a6e90a69d44db99c341a64a65b6e3147dc97c327aa",
        "of_activo": false,
        "telegram_activo": false,
        "created_at": "2026-03-25T22:50:24.379983+00:00",
        "updated_at": "2026-03-25T22:50:25.852132+00:00",
        "invite_link": "https://t.me/+d0klpt_4nuU3NmE0",
        "invite_link_created_at": "2026-03-25T22:50:24.257+00:00",
        "last_bot_action": null,
        "active_flow": null,
        "winback_sent": false,
        "telegram_user_id": null
      },
      {
        "id": "6440f2d3-d1ae-4b51-a92a-b347127bc465",
        "visitor_id": "test-f25-final-1774479035615",
        "fingerprint_hash": "fp_test-f25-final-1774479035615",
        "modelo_id": "MODEL_ID_PLACEHOLDER",
        "utm_source": "reddit",
        "idioma": "es",
        "dispositivo": "mobile",
        "user_agent": "f25-final",
        "ip_hash": "c0d5a166315fb25668143f0eebe02cd5bd539c01372f01f3e63e2b570c05eb60",
        "of_activo": false,
        "telegram_activo": true,
        "created_at": "2026-03-25T22:50:36.993159+00:00",
        "updated_at": "2026-03-25T22:55:28.980425+00:00",
        "invite_link": "https://t.me/+RUW9RYGLOBA2Y2E0",
        "invite_link_created_at": "2026-03-25T22:50:36.956+00:00",
        "last_bot_action": "2026-03-25T22:55:28.657+00:00",
        "active_flow": "3",
        "winback_sent": false,
        "telegram_user_id": "999777"
      },
      {
        "id": "adbcd4ea-41ca-462d-8d59-08e73b80e195",
        "visitor_id": "35f9f7e6-5c57-46c6-a205-c0e8e0f11e2d",
        "fingerprint_hash": "smoke_fp_1f32a8fcecc442368223d5aafbafdef1",
        "modelo_id": "MODEL_ID_PLACEHOLDER",
        "utm_source": "smoke",
        "idioma": "es",
        "dispositivo": "mobile",
        "user_agent": "smoke-daily",
        "ip_hash": "7cbd35555dbd08a1dd84077caa2eed269dafed5f841c1ebee16018617d82fa50",
        "of_activo": false,
        "telegram_activo": false,
        "created_at": "2026-03-25T23:10:39.675754+00:00",
        "updated_at": "2026-03-25T23:10:41.279355+00:00",
        "invite_link": "https://t.me/+Afax7buFALM0NTM0",
        "invite_link_created_at": "2026-03-25T23:10:39.556+00:00",
        "last_bot_action": null,
        "active_flow": null,
        "winback_sent": false,
        "telegram_user_id": null
      },
      {
        "id": "a222c6f7-2d91-4c69-b6e6-1474c4b868c2",
        "visitor_id": "531c55fd-49af-48fe-9df4-64bbd349369e",
        "fingerprint_hash": "smoke_fp_f305fc492bfc443087826046ac0feca0",
        "modelo_id": "MODEL_ID_PLACEHOLDER",
        "utm_source": "smoke",
        "idioma": "es",
        "dispositivo": "mobile",
        "user_agent": "smoke-daily",
        "ip_hash": "1d515f89853c4cca1dcc09611b5e04963b1fc21705cc373a1695613bd2d350ba",
        "of_activo": false,
        "telegram_activo": false,
        "created_at": "2026-03-25T23:11:20.507947+00:00",
        "updated_at": "2026-03-25T23:11:21.720628+00:00",
        "invite_link": "https://t.me/+FIDnHNGDhjFhZTU0",
        "invite_link_created_at": "2026-03-25T23:11:20.468+00:00",
        "last_bot_action": null,
        "active_flow": null,
        "winback_sent": false,
        "telegram_user_id": null
      },
      {
        "id": "d83385ac-204f-40de-a706-4afb67399ca1",
        "visitor_id": "545e6caf-52b2-4de8-9933-062bb5f5c506",
        "fingerprint_hash": "smoke_fp_43b016ca67ff4f1896ea0242110bc008",
        "modelo_id": "MODEL_ID_PLACEHOLDER",
        "utm_source": "smoke",
        "idioma": "es",
        "dispositivo": "mobile",
        "user_agent": "smoke-daily",
        "ip_hash": "f6e7cc919636d2f3eb0cf40b93d1062bbd378c68dd8f413e14706d2b0ecb5c15",
        "of_activo": false,
        "telegram_activo": false,
        "created_at": "2026-03-25T23:14:13.174894+00:00",
        "updated_at": "2026-03-25T23:14:14.458893+00:00",
        "invite_link": "https://t.me/+97DJZFssswwzOGU0",
        "invite_link_created_at": "2026-03-25T23:14:13.125+00:00",
        "last_bot_action": null,
        "active_flow": null,
        "winback_sent": false,
        "telegram_user_id": null
      }
    ],
    "eventos": [
      {
        "id": "62a7fa70-0125-41ce-85c8-f4d1917f16f4",
        "request_id": "b3f67f5a-669a-4c3a-bfca-5ab0792e76e1",
        "visitor_id": "1482c50a-b8e7-44ed-a00a-8c660f95424f",
        "modelo_id": "MODEL_ID_PLACEHOLDER",
        "boton_clickado": "onlyfans",
        "utm_source": "instagram",
        "idioma": "es",
        "dispositivo": "mobile",
        "user_agent": "proxy-smoke-test",
        "fingerprint_hash": "fp_hash_test_123",
        "created_at": "2026-03-25T16:15:35.447569+00:00"
      },
      {
        "id": "de745af7-06e7-4bec-8819-5de2519f4b1b",
        "request_id": "9b466f35-c43e-4a50-b6f4-6429c0feb322",
        "visitor_id": "6d484e1d-b2f0-48e2-8b90-b401f7beb282",
        "modelo_id": "MODEL_ID_PLACEHOLDER",
        "boton_clickado": "onlyfans",
        "utm_source": "instagram",
        "idioma": "es",
        "dispositivo": "mobile",
        "user_agent": "proxy-smoke-test",
        "fingerprint_hash": "fp_hash_test_123",
        "created_at": "2026-03-25T16:15:44.137609+00:00"
      },
      {
        "id": "4111ce03-0619-4f6c-9ce6-ac1a86fc5651",
        "request_id": "ee3deaa8-3d52-494b-b38b-1106c07772e2",
        "visitor_id": "08126fc3-f423-42af-ab2a-8fc957dddfbf",
        "modelo_id": "MODEL_ID_PLACEHOLDER",
        "boton_clickado": "onlyfans",
        "utm_source": "instagram",
        "idioma": "es",
        "dispositivo": "mobile",
        "user_agent": "proxy-smoke-test",
        "fingerprint_hash": "fp_hash_test_123",
        "created_at": "2026-03-25T16:16:35.428354+00:00"
      },
      {
        "id": "a2f9bba7-41d1-47a6-8da3-4c47f3c4a86f",
        "request_id": "b4ca887b-ffb5-4aea-b2d6-f397d9794cc0",
        "visitor_id": "54a2457a-9790-4cf1-ac8d-304f0d1d453e",
        "modelo_id": "MODEL_ID_PLACEHOLDER",
        "boton_clickado": "onlyfans",
        "utm_source": "instagram",
        "idioma": "es",
        "dispositivo": "mobile",
        "user_agent": "e2e-script",
        "fingerprint_hash": "fp_666ee08a3d694e8fb5cf21d6d4f13fee",
        "created_at": "2026-03-25T16:57:51.557266+00:00"
      },
      {
        "id": "edee985c-e6e3-4099-9014-72fa7254673f",
        "request_id": "1d579358-0b45-42b7-bd17-cc7cf22495df",
        "visitor_id": "0413bc0b-b98e-450d-abed-8a2f356f90b1",
        "modelo_id": "MODEL_ID_PLACEHOLDER",
        "boton_clickado": "onlyfans",
        "utm_source": "stress",
        "idioma": "es",
        "dispositivo": "mobile",
        "user_agent": "stress-concurrency",
        "fingerprint_hash": "fp_conc_bc264b45d570474880ef8d0637787259",
        "created_at": "2026-03-25T16:58:11.651417+00:00"
      },
      {
        "id": "556b4e25-0579-4fdc-b7ed-46973812aca1",
        "request_id": "7ac387a6-7d62-4ae4-83e9-2e85d2a4e2f8",
        "visitor_id": "stress-1774457902851",
        "modelo_id": "MODEL_ID_PLACEHOLDER",
        "boton_clickado": "onlyfans",
        "utm_source": "stress",
        "idioma": "es",
        "dispositivo": "mobile",
        "user_agent": "stress-bulk",
        "fingerprint_hash": "fp_stress_484e376783404763ac3f4a85f78cdb78",
        "created_at": "2026-03-25T16:58:23.626157+00:00"
      },
      {
        "id": "691d1eaa-6687-4eb3-9f06-6984f9beb89a",
        "request_id": "af3cdb06-a3b8-4e6a-ba25-20091512a2d1",
        "visitor_id": "stress-1774457902851",
        "modelo_id": "MODEL_ID_PLACEHOLDER",
        "boton_clickado": "telegram",
        "utm_source": "stress",
        "idioma": "es",
        "dispositivo": "mobile",
        "user_agent": "stress-bulk",
        "fingerprint_hash": "fp_stress_484e376783404763ac3f4a85f78cdb78",
        "created_at": "2026-03-25T16:58:24.152715+00:00"
      },
      {
        "id": "1c0be59c-3d09-455c-b89d-733f3a24af48",
        "request_id": "9c37eb1e-e1a4-4489-8a04-1130ec71ed53",
        "visitor_id": "stress-1774457902851",
        "modelo_id": "MODEL_ID_PLACEHOLDER",
        "boton_clickado": "onlyfans",
        "utm_source": "stress",
        "idioma": "es",
        "dispositivo": "mobile",
        "user_agent": "stress-bulk",
        "fingerprint_hash": "fp_stress_484e376783404763ac3f4a85f78cdb78",
        "created_at": "2026-03-25T16:58:24.590832+00:00"
      },
      {
        "id": "e422e2bc-db80-4616-b927-48a2ba40ede9",
        "request_id": "f08f83ed-6743-4bd8-b52a-058ac27bceb3",
        "visitor_id": "stress-1774457902851",
        "modelo_id": "MODEL_ID_PLACEHOLDER",
        "boton_clickado": "telegram",
        "utm_source": "stress",
        "idioma": "es",
        "dispositivo": "mobile",
        "user_agent": "stress-bulk",
        "fingerprint_hash": "fp_stress_484e376783404763ac3f4a85f78cdb78",
        "created_at": "2026-03-25T16:58:25.061444+00:00"
      },
      {
        "id": "cd872b8b-4436-4adf-bd0e-5a0219a3351c",
        "request_id": "f12be85d-dc31-4094-a020-d3c0adf3dbea",
        "visitor_id": "stress-1774457902851",
        "modelo_id": "MODEL_ID_PLACEHOLDER",
        "boton_clickado": "onlyfans",
        "utm_source": "stress",
        "idioma": "es",
        "dispositivo": "mobile",
        "user_agent": "stress-bulk",
        "fingerprint_hash": "fp_stress_484e376783404763ac3f4a85f78cdb78",
        "created_at": "2026-03-25T16:58:25.473763+00:00"
      },
      {
        "id": "8e0317b9-25bf-4f2b-85e7-be0505d953a3",
        "request_id": "722c2c17-0728-49b3-a4b5-31b831c6f42b",
        "visitor_id": "stress-1774457902851",
        "modelo_id": "MODEL_ID_PLACEHOLDER",
        "boton_clickado": "telegram",
        "utm_source": "stress",
        "idioma": "es",
        "dispositivo": "mobile",
        "user_agent": "stress-bulk",
        "fingerprint_hash": "fp_stress_484e376783404763ac3f4a85f78cdb78",
        "created_at": "2026-03-25T16:58:25.847061+00:00"
      },
      {
        "id": "7b0f7a8a-f7f2-4aff-b652-57bd0de49c0d",
        "request_id": "8aac1f4c-3129-48c3-9008-3e5bdf8b82b3",
        "visitor_id": "stress-1774457902851",
        "modelo_id": "MODEL_ID_PLACEHOLDER",
        "boton_clickado": "onlyfans",
        "utm_source": "stress",
        "idioma": "es",
        "dispositivo": "mobile",
        "user_agent": "stress-bulk",
        "fingerprint_hash": "fp_stress_484e376783404763ac3f4a85f78cdb78",
        "created_at": "2026-03-25T16:58:26.293291+00:00"
      },
      {
        "id": "a6d4cf5c-b923-4c57-b6fe-6194b939f164",
        "request_id": "7af33479-a44f-4778-9bd2-f4bd02a950a7",
        "visitor_id": "stress-1774457902851",
        "modelo_id": "MODEL_ID_PLACEHOLDER",
        "boton_clickado": "telegram",
        "utm_source": "stress",
        "idioma": "es",
        "dispositivo": "mobile",
        "user_agent": "stress-bulk",
        "fingerprint_hash": "fp_stress_484e376783404763ac3f4a85f78cdb78",
        "created_at": "2026-03-25T16:58:26.788647+00:00"
      },
      {
        "id": "2351268b-ca2a-4535-af93-27d93001f657",
        "request_id": "215769a8-6ca7-40d9-9e94-c8d7df158b74",
        "visitor_id": "stress-1774457902851",
        "modelo_id": "MODEL_ID_PLACEHOLDER",
        "boton_clickado": "onlyfans",
        "utm_source": "stress",
        "idioma": "es",
        "dispositivo": "mobile",
        "user_agent": "stress-bulk",
        "fingerprint_hash": "fp_stress_484e376783404763ac3f4a85f78cdb78",
        "created_at": "2026-03-25T16:58:27.252409+00:00"
      },
      {
        "id": "2737be3d-b729-45e3-b9a0-28ed200ddc6f",
        "request_id": "de216362-6c42-48a5-abe1-ff95e23b976a",
        "visitor_id": "stress-1774457902851",
        "modelo_id": "MODEL_ID_PLACEHOLDER",
        "boton_clickado": "telegram",
        "utm_source": "stress",
        "idioma": "es",
        "dispositivo": "mobile",
        "user_agent": "stress-bulk",
        "fingerprint_hash": "fp_stress_484e376783404763ac3f4a85f78cdb78",
        "created_at": "2026-03-25T16:58:27.651175+00:00"
      },
      {
        "id": "a8b160df-dab6-4f68-8b1b-71ddbf945309",
        "request_id": "ce99458c-4028-47f8-999f-5aa0afc2bc51",
        "visitor_id": "stress-1774457902851",
        "modelo_id": "MODEL_ID_PLACEHOLDER",
        "boton_clickado": "onlyfans",
        "utm_source": "stress",
        "idioma": "es",
        "dispositivo": "mobile",
        "user_agent": "stress-bulk",
        "fingerprint_hash": "fp_stress_484e376783404763ac3f4a85f78cdb78",
        "created_at": "2026-03-25T16:58:28.046229+00:00"
      },
      {
        "id": "048cb329-ec57-4db2-8c59-0bac418a339c",
        "request_id": "daedb1fc-3a9e-4a6c-b2b9-f17dbe1d1cf1",
        "visitor_id": "stress-1774457902851",
        "modelo_id": "MODEL_ID_PLACEHOLDER",
        "boton_clickado": "telegram",
        "utm_source": "stress",
        "idioma": "es",
        "dispositivo": "mobile",
        "user_agent": "stress-bulk",
        "fingerprint_hash": "fp_stress_484e376783404763ac3f4a85f78cdb78",
        "created_at": "2026-03-25T16:58:28.51864+00:00"
      },
      {
        "id": "ff63ec52-6e07-406b-bbdc-8a6aa168b968",
        "request_id": "3d3eb18b-82e3-4e9e-9927-7a69f16f9a6b",
        "visitor_id": "stress-1774457902851",
        "modelo_id": "MODEL_ID_PLACEHOLDER",
        "boton_clickado": "onlyfans",
        "utm_source": "stress",
        "idioma": "es",
        "dispositivo": "mobile",
        "user_agent": "stress-bulk",
        "fingerprint_hash": "fp_stress_484e376783404763ac3f4a85f78cdb78",
        "created_at": "2026-03-25T16:58:28.994147+00:00"
      },
      {
        "id": "cad66f5c-93bc-4274-845e-90e87938d3c9",
        "request_id": "7d942b6a-3ce3-4ca3-9359-47750f8a404d",
        "visitor_id": "stress-1774457902851",
        "modelo_id": "MODEL_ID_PLACEHOLDER",
        "boton_clickado": "telegram",
        "utm_source": "stress",
        "idioma": "es",
        "dispositivo": "mobile",
        "user_agent": "stress-bulk",
        "fingerprint_hash": "fp_stress_484e376783404763ac3f4a85f78cdb78",
        "created_at": "2026-03-25T16:58:29.417889+00:00"
      },
      {
        "id": "e9e5197a-95c4-47ff-b53f-ddc2239edf2d",
        "request_id": "4b0731cf-0c0a-4357-b0e5-90958e6cf13d",
        "visitor_id": "stress-1774457902851",
        "modelo_id": "MODEL_ID_PLACEHOLDER",
        "boton_clickado": "onlyfans",
        "utm_source": "stress",
        "idioma": "es",
        "dispositivo": "mobile",
        "user_agent": "stress-bulk",
        "fingerprint_hash": "fp_stress_484e376783404763ac3f4a85f78cdb78",
        "created_at": "2026-03-25T16:58:29.896195+00:00"
      },
      {
        "id": "ce7a2ef0-1e5b-4320-b1b2-3a26a28ec48e",
        "request_id": "416388eb-3b2d-4cec-ac93-26c0dfd645c5",
        "visitor_id": "stress-1774457902851",
        "modelo_id": "MODEL_ID_PLACEHOLDER",
        "boton_clickado": "telegram",
        "utm_source": "stress",
        "idioma": "es",
        "dispositivo": "mobile",
        "user_agent": "stress-bulk",
        "fingerprint_hash": "fp_stress_484e376783404763ac3f4a85f78cdb78",
        "created_at": "2026-03-25T16:58:30.192966+00:00"
      },
      {
        "id": "e88a0a5f-9fb6-4f5d-889e-bca8d34f717c",
        "request_id": "da76047d-19c2-40e6-9089-0239e37de991",
        "visitor_id": "stress-1774457902851",
        "modelo_id": "MODEL_ID_PLACEHOLDER",
        "boton_clickado": "onlyfans",
        "utm_source": "stress",
        "idioma": "es",
        "dispositivo": "mobile",
        "user_agent": "stress-bulk",
        "fingerprint_hash": "fp_stress_484e376783404763ac3f4a85f78cdb78",
        "created_at": "2026-03-25T16:58:30.696387+00:00"
      },
      {
        "id": "40736120-425a-4a86-be2c-d497d7eb8ad4",
        "request_id": "7cc09ce3-5dd4-4ed0-ab71-03090a2a2df2",
        "visitor_id": "stress-1774457902851",
        "modelo_id": "MODEL_ID_PLACEHOLDER",
        "boton_clickado": "telegram",
        "utm_source": "stress",
        "idioma": "es",
        "dispositivo": "mobile",
        "user_agent": "stress-bulk",
        "fingerprint_hash": "fp_stress_484e376783404763ac3f4a85f78cdb78",
        "created_at": "2026-03-25T16:58:31.149361+00:00"
      },
      {
        "id": "6c8b0a39-4b89-4948-bbf0-c83e74295cec",
        "request_id": "a9aadce9-a918-4d97-8850-1d78a279b45e",
        "visitor_id": "stress-1774457902851",
        "modelo_id": "MODEL_ID_PLACEHOLDER",
        "boton_clickado": "onlyfans",
        "utm_source": "stress",
        "idioma": "es",
        "dispositivo": "mobile",
        "user_agent": "stress-bulk",
        "fingerprint_hash": "fp_stress_484e376783404763ac3f4a85f78cdb78",
        "created_at": "2026-03-25T16:58:31.57031+00:00"
      },
      {
        "id": "d94d265b-29bf-4035-b821-52b46e9c5745",
        "request_id": "8035e88f-1711-48d3-823f-63ccff12f965",
        "visitor_id": "stress-1774457902851",
        "modelo_id": "MODEL_ID_PLACEHOLDER",
        "boton_clickado": "telegram",
        "utm_source": "stress",
        "idioma": "es",
        "dispositivo": "mobile",
        "user_agent": "stress-bulk",
        "fingerprint_hash": "fp_stress_484e376783404763ac3f4a85f78cdb78",
        "created_at": "2026-03-25T16:58:31.921048+00:00"
      },
      {
        "id": "e919c080-31a7-4bb6-8347-5cf792419300",
        "request_id": "0f57e97a-1a92-4c5f-a3cb-3442f6f7cdb6",
        "visitor_id": "stress-1774457902851",
        "modelo_id": "MODEL_ID_PLACEHOLDER",
        "boton_clickado": "onlyfans",
        "utm_source": "stress",
        "idioma": "es",
        "dispositivo": "mobile",
        "user_agent": "stress-bulk",
        "fingerprint_hash": "fp_stress_484e376783404763ac3f4a85f78cdb78",
        "created_at": "2026-03-25T16:58:32.386162+00:00"
      },
      {
        "id": "89cdc179-038e-41f9-861b-4f78eaeb2c4e",
        "request_id": "81b1bc39-e891-41cd-a2fb-91cb0b5498c9",
        "visitor_id": "stress-1774457902851",
        "modelo_id": "MODEL_ID_PLACEHOLDER",
        "boton_clickado": "telegram",
        "utm_source": "stress",
        "idioma": "es",
        "dispositivo": "mobile",
        "user_agent": "stress-bulk",
        "fingerprint_hash": "fp_stress_484e376783404763ac3f4a85f78cdb78",
        "created_at": "2026-03-25T16:58:32.896253+00:00"
      },
      {
        "id": "7cf38983-6dbc-425a-9f98-bee66d8aa137",
        "request_id": "67f77be0-b374-41d2-b02e-5162a6e78929",
        "visitor_id": "stress-1774457902851",
        "modelo_id": "MODEL_ID_PLACEHOLDER",
        "boton_clickado": "onlyfans",
        "utm_source": "stress",
        "idioma": "es",
        "dispositivo": "mobile",
        "user_agent": "stress-bulk",
        "fingerprint_hash": "fp_stress_484e376783404763ac3f4a85f78cdb78",
        "created_at": "2026-03-25T16:58:33.242113+00:00"
      },
      {
        "id": "ae5125a1-36a8-44b5-b19d-69f1a0e76405",
        "request_id": "8d5a5e7c-5848-449e-9959-1b85b5123223",
        "visitor_id": "stress-1774457902851",
        "modelo_id": "MODEL_ID_PLACEHOLDER",
        "boton_clickado": "telegram",
        "utm_source": "stress",
        "idioma": "es",
        "dispositivo": "mobile",
        "user_agent": "stress-bulk",
        "fingerprint_hash": "fp_stress_484e376783404763ac3f4a85f78cdb78",
        "created_at": "2026-03-25T16:58:33.637062+00:00"
      },
      {
        "id": "86952562-7077-434a-a5a1-7a095ed612df",
        "request_id": "548e36f6-e38a-4f24-911f-d226524549d8",
        "visitor_id": "stress-1774457902851",
        "modelo_id": "MODEL_ID_PLACEHOLDER",
        "boton_clickado": "onlyfans",
        "utm_source": "stress",
        "idioma": "es",
        "dispositivo": "mobile",
        "user_agent": "stress-bulk",
        "fingerprint_hash": "fp_stress_484e376783404763ac3f4a85f78cdb78",
        "created_at": "2026-03-25T16:58:34.047954+00:00"
      },
      {
        "id": "66115b85-254e-44d3-abdb-87c13e255a77",
        "request_id": "b34fc8ba-0b03-469e-9ec5-58a666df263c",
        "visitor_id": "dfd5b49a-0e34-4680-983e-4e6d072223dd",
        "modelo_id": "MODEL_ID_PLACEHOLDER",
        "boton_clickado": "onlyfans",
        "utm_source": "instagram",
        "idioma": "es",
        "dispositivo": "mobile",
        "user_agent": "e2e-script",
        "fingerprint_hash": "fp_2d72023bb2e94ba4a3ef38ab407bb936",
        "created_at": "2026-03-25T16:58:54.483827+00:00"
      },
      {
        "id": "0552889d-cbd2-487b-b864-68a5adbf26ff",
        "request_id": "d98eeac1-5b61-4585-9c5f-938040cdd4f3",
        "visitor_id": "743b6c10-9d53-42b6-8917-75304e25b425",
        "modelo_id": "MODEL_ID_PLACEHOLDER",
        "boton_clickado": "onlyfans",
        "utm_source": "stress",
        "idioma": "es",
        "dispositivo": "mobile",
        "user_agent": "stress-concurrency",
        "fingerprint_hash": "fp_concurrency_d8770b38b84f41c689d8aef54f9a573a",
        "created_at": "2026-03-25T16:58:58.296064+00:00"
      },
      {
        "id": "927a7aec-5c50-4d5f-af58-a8810b099335",
        "request_id": "96a8a6a8-31ea-43aa-8e1e-a05456a4c032",
        "visitor_id": "stress-1774457938570",
        "modelo_id": "MODEL_ID_PLACEHOLDER",
        "boton_clickado": "onlyfans",
        "utm_source": "stress",
        "idioma": "es",
        "dispositivo": "mobile",
        "user_agent": "stress-bulk",
        "fingerprint_hash": "fp_stress_393304cecc784f219fc20ac7c9ae1491",
        "created_at": "2026-03-25T16:58:59.231555+00:00"
      },
      {
        "id": "a3f39505-b461-44fa-bf57-957c57d9934d",
        "request_id": "3f0e8fda-22d6-40b1-b298-e9957634a40f",
        "visitor_id": "stress-1774457938570",
        "modelo_id": "MODEL_ID_PLACEHOLDER",
        "boton_clickado": "telegram",
        "utm_source": "stress",
        "idioma": "es",
        "dispositivo": "mobile",
        "user_agent": "stress-bulk",
        "fingerprint_hash": "fp_stress_393304cecc784f219fc20ac7c9ae1491",
        "created_at": "2026-03-25T16:58:59.685893+00:00"
      },
      {
        "id": "61f9c50a-c40e-4d43-95c2-4583f13122ca",
        "request_id": "a2f08fcd-c612-4441-bad7-740e64c4cdc2",
        "visitor_id": "stress-1774457938570",
        "modelo_id": "MODEL_ID_PLACEHOLDER",
        "boton_clickado": "onlyfans",
        "utm_source": "stress",
        "idioma": "es",
        "dispositivo": "mobile",
        "user_agent": "stress-bulk",
        "fingerprint_hash": "fp_stress_393304cecc784f219fc20ac7c9ae1491",
        "created_at": "2026-03-25T16:59:00.146961+00:00"
      },
      {
        "id": "f0a74a4f-0008-42bd-b521-39b932c4c0b5",
        "request_id": "117ae898-0415-458d-ac2e-ee9a09eca9f2",
        "visitor_id": "stress-1774457938570",
        "modelo_id": "MODEL_ID_PLACEHOLDER",
        "boton_clickado": "telegram",
        "utm_source": "stress",
        "idioma": "es",
        "dispositivo": "mobile",
        "user_agent": "stress-bulk",
        "fingerprint_hash": "fp_stress_393304cecc784f219fc20ac7c9ae1491",
        "created_at": "2026-03-25T16:59:00.648556+00:00"
      },
      {
        "id": "cc72795b-975f-476e-a53b-078175722e7e",
        "request_id": "feef9f35-457f-460f-bbd1-5d38b8d7293a",
        "visitor_id": "stress-1774457938570",
        "modelo_id": "MODEL_ID_PLACEHOLDER",
        "boton_clickado": "onlyfans",
        "utm_source": "stress",
        "idioma": "es",
        "dispositivo": "mobile",
        "user_agent": "stress-bulk",
        "fingerprint_hash": "fp_stress_393304cecc784f219fc20ac7c9ae1491",
        "created_at": "2026-03-25T16:59:01.063776+00:00"
      },
      {
        "id": "3044d8ce-7e4b-465e-9282-13ca4d741f2d",
        "request_id": "40c63611-4196-43dd-b907-1224dbd04e46",
        "visitor_id": "stress-1774457938570",
        "modelo_id": "MODEL_ID_PLACEHOLDER",
        "boton_clickado": "telegram",
        "utm_source": "stress",
        "idioma": "es",
        "dispositivo": "mobile",
        "user_agent": "stress-bulk",
        "fingerprint_hash": "fp_stress_393304cecc784f219fc20ac7c9ae1491",
        "created_at": "2026-03-25T16:59:01.484265+00:00"
      },
      {
        "id": "13b52fc0-d797-4697-9993-d0ce5504266c",
        "request_id": "358aa53c-abd6-4f2c-9689-d68ee9dc9d65",
        "visitor_id": "stress-1774457938570",
        "modelo_id": "MODEL_ID_PLACEHOLDER",
        "boton_clickado": "onlyfans",
        "utm_source": "stress",
        "idioma": "es",
        "dispositivo": "mobile",
        "user_agent": "stress-bulk",
        "fingerprint_hash": "fp_stress_393304cecc784f219fc20ac7c9ae1491",
        "created_at": "2026-03-25T16:59:01.96932+00:00"
      },
      {
        "id": "84f48d50-38f4-4d80-a797-a57b76237f07",
        "request_id": "5abe294a-0772-4741-b597-3235cebde759",
        "visitor_id": "stress-1774457938570",
        "modelo_id": "MODEL_ID_PLACEHOLDER",
        "boton_clickado": "telegram",
        "utm_source": "stress",
        "idioma": "es",
        "dispositivo": "mobile",
        "user_agent": "stress-bulk",
        "fingerprint_hash": "fp_stress_393304cecc784f219fc20ac7c9ae1491",
        "created_at": "2026-03-25T16:59:05.740349+00:00"
      },
      {
        "id": "2397ea19-d271-44fa-8e5f-cef839a91a1e",
        "request_id": "f341596e-a04a-40c1-a7c8-78b76b33594b",
        "visitor_id": "stress-1774457938570",
        "modelo_id": "MODEL_ID_PLACEHOLDER",
        "boton_clickado": "telegram",
        "utm_source": "stress",
        "idioma": "es",
        "dispositivo": "mobile",
        "user_agent": "stress-bulk",
        "fingerprint_hash": "fp_stress_393304cecc784f219fc20ac7c9ae1491",
        "created_at": "2026-03-25T16:59:02.380215+00:00"
      },
      {
        "id": "1860b5bd-cc73-48cd-bc36-a753a64f5dfa",
        "request_id": "e8477e50-2561-40d3-b816-a12dbdc7b374",
        "visitor_id": "stress-1774457938570",
        "modelo_id": "MODEL_ID_PLACEHOLDER",
        "boton_clickado": "onlyfans",
        "utm_source": "stress",
        "idioma": "es",
        "dispositivo": "mobile",
        "user_agent": "stress-bulk",
        "fingerprint_hash": "fp_stress_393304cecc784f219fc20ac7c9ae1491",
        "created_at": "2026-03-25T16:59:06.070472+00:00"
      },
      {
        "id": "eee14207-54e0-4f54-82b2-de3331acb829",
        "request_id": "9bb90fb7-1a29-4d3c-9ff0-081637838718",
        "visitor_id": "stress-1774457938570",
        "modelo_id": "MODEL_ID_PLACEHOLDER",
        "boton_clickado": "onlyfans",
        "utm_source": "stress",
        "idioma": "es",
        "dispositivo": "mobile",
        "user_agent": "stress-bulk",
        "fingerprint_hash": "fp_stress_393304cecc784f219fc20ac7c9ae1491",
        "created_at": "2026-03-25T16:59:02.744149+00:00"
      },
      {
        "id": "c993cfcb-37ea-4e6f-854e-35b976a500fa",
        "request_id": "7034cab1-e770-4aa4-948b-d5d0acad84ca",
        "visitor_id": "stress-1774457938570",
        "modelo_id": "MODEL_ID_PLACEHOLDER",
        "boton_clickado": "telegram",
        "utm_source": "stress",
        "idioma": "es",
        "dispositivo": "mobile",
        "user_agent": "stress-bulk",
        "fingerprint_hash": "fp_stress_393304cecc784f219fc20ac7c9ae1491",
        "created_at": "2026-03-25T16:59:06.498054+00:00"
      },
      {
        "id": "05d1279f-8983-43b7-865f-beab4b19e710",
        "request_id": "32312782-437d-4e64-8313-8df687fa24be",
        "visitor_id": "stress-1774457938570",
        "modelo_id": "MODEL_ID_PLACEHOLDER",
        "boton_clickado": "telegram",
        "utm_source": "stress",
        "idioma": "es",
        "dispositivo": "mobile",
        "user_agent": "stress-bulk",
        "fingerprint_hash": "fp_stress_393304cecc784f219fc20ac7c9ae1491",
        "created_at": "2026-03-25T16:59:03.130713+00:00"
      },
      {
        "id": "c4d344b2-fda4-420b-97ad-2d121aa7ea87",
        "request_id": "61a6a3ed-a296-4d38-bd64-4e39a733e476",
        "visitor_id": "stress-1774457938570",
        "modelo_id": "MODEL_ID_PLACEHOLDER",
        "boton_clickado": "onlyfans",
        "utm_source": "stress",
        "idioma": "es",
        "dispositivo": "mobile",
        "user_agent": "stress-bulk",
        "fingerprint_hash": "fp_stress_393304cecc784f219fc20ac7c9ae1491",
        "created_at": "2026-03-25T16:59:06.984557+00:00"
      },
      {
        "id": "f5fae45d-2848-4538-b116-6bcaa2dcd616",
        "request_id": "67384554-644d-46f7-8d2a-62938163ab48",
        "visitor_id": "stress-1774457938570",
        "modelo_id": "MODEL_ID_PLACEHOLDER",
        "boton_clickado": "onlyfans",
        "utm_source": "stress",
        "idioma": "es",
        "dispositivo": "mobile",
        "user_agent": "stress-bulk",
        "fingerprint_hash": "fp_stress_393304cecc784f219fc20ac7c9ae1491",
        "created_at": "2026-03-25T16:59:03.586481+00:00"
      },
      {
        "id": "b04b244b-f1f8-4183-a4e6-7758d0832ee9",
        "request_id": "504c5f0e-8887-4f56-be15-34243690e866",
        "visitor_id": "stress-1774457938570",
        "modelo_id": "MODEL_ID_PLACEHOLDER",
        "boton_clickado": "telegram",
        "utm_source": "stress",
        "idioma": "es",
        "dispositivo": "mobile",
        "user_agent": "stress-bulk",
        "fingerprint_hash": "fp_stress_393304cecc784f219fc20ac7c9ae1491",
        "created_at": "2026-03-25T16:59:04.045256+00:00"
      },
      {
        "id": "3d52d5e4-8650-444f-b277-6219d2628a13",
        "request_id": "73566341-7d98-43c7-9599-b6fcd2e692b1",
        "visitor_id": "stress-1774457938570",
        "modelo_id": "MODEL_ID_PLACEHOLDER",
        "boton_clickado": "onlyfans",
        "utm_source": "stress",
        "idioma": "es",
        "dispositivo": "mobile",
        "user_agent": "stress-bulk",
        "fingerprint_hash": "fp_stress_393304cecc784f219fc20ac7c9ae1491",
        "created_at": "2026-03-25T16:59:04.457156+00:00"
      },
      {
        "id": "00ff0ec0-b7b2-4c51-bf45-9697d33887c6",
        "request_id": "df95fe21-293b-4131-be8a-74a1a8f01db1",
        "visitor_id": "stress-1774457938570",
        "modelo_id": "MODEL_ID_PLACEHOLDER",
        "boton_clickado": "telegram",
        "utm_source": "stress",
        "idioma": "es",
        "dispositivo": "mobile",
        "user_agent": "stress-bulk",
        "fingerprint_hash": "fp_stress_393304cecc784f219fc20ac7c9ae1491",
        "created_at": "2026-03-25T16:59:04.858962+00:00"
      },
      {
        "id": "c972f4a5-e6f1-48c0-b77c-b128a6821ef9",
        "request_id": "c680a308-af4d-44ff-8b0c-f53007b92595",
        "visitor_id": "stress-1774457938570",
        "modelo_id": "MODEL_ID_PLACEHOLDER",
        "boton_clickado": "onlyfans",
        "utm_source": "stress",
        "idioma": "es",
        "dispositivo": "mobile",
        "user_agent": "stress-bulk",
        "fingerprint_hash": "fp_stress_393304cecc784f219fc20ac7c9ae1491",
        "created_at": "2026-03-25T16:59:05.291935+00:00"
      },
      {
        "id": "f3b62c7d-18f2-4108-9dbc-0eb1a5abe7a1",
        "request_id": "0b8c0e6a-2d76-4db3-80bd-cea94d23322e",
        "visitor_id": "stress-1774457938570",
        "modelo_id": "MODEL_ID_PLACEHOLDER",
        "boton_clickado": "telegram",
        "utm_source": "stress",
        "idioma": "es",
        "dispositivo": "mobile",
        "user_agent": "stress-bulk",
        "fingerprint_hash": "fp_stress_393304cecc784f219fc20ac7c9ae1491",
        "created_at": "2026-03-25T16:59:07.347265+00:00"
      },
      {
        "id": "7a3e8922-c29e-4063-9363-4fe328a8e5fc",
        "request_id": "2d1812f3-ddd5-4b19-8118-a58edc7e7e28",
        "visitor_id": "stress-1774457938570",
        "modelo_id": "MODEL_ID_PLACEHOLDER",
        "boton_clickado": "onlyfans",
        "utm_source": "stress",
        "idioma": "es",
        "dispositivo": "mobile",
        "user_agent": "stress-bulk",
        "fingerprint_hash": "fp_stress_393304cecc784f219fc20ac7c9ae1491",
        "created_at": "2026-03-25T16:59:07.843561+00:00"
      },
      {
        "id": "65fc8a83-72c0-4a8d-9dbe-20c782ec6f56",
        "request_id": "520c807f-ae73-419d-a0de-17127a296ce1",
        "visitor_id": "stress-1774457938570",
        "modelo_id": "MODEL_ID_PLACEHOLDER",
        "boton_clickado": "telegram",
        "utm_source": "stress",
        "idioma": "es",
        "dispositivo": "mobile",
        "user_agent": "stress-bulk",
        "fingerprint_hash": "fp_stress_393304cecc784f219fc20ac7c9ae1491",
        "created_at": "2026-03-25T16:59:08.287241+00:00"
      },
      {
        "id": "1ce54eaa-6122-4caa-bc1c-62cd383f490c",
        "request_id": "e43bde77-9564-444e-8eb5-5944bed3ffaf",
        "visitor_id": "stress-1774457938570",
        "modelo_id": "MODEL_ID_PLACEHOLDER",
        "boton_clickado": "onlyfans",
        "utm_source": "stress",
        "idioma": "es",
        "dispositivo": "mobile",
        "user_agent": "stress-bulk",
        "fingerprint_hash": "fp_stress_393304cecc784f219fc20ac7c9ae1491",
        "created_at": "2026-03-25T16:59:08.662123+00:00"
      },
      {
        "id": "bc0e20d9-bb92-441f-9dc5-e83f357066a6",
        "request_id": "3824c79c-2f04-4e08-b12b-cd626db52dfd",
        "visitor_id": "stress-1774457938570",
        "modelo_id": "MODEL_ID_PLACEHOLDER",
        "boton_clickado": "telegram",
        "utm_source": "stress",
        "idioma": "es",
        "dispositivo": "mobile",
        "user_agent": "stress-bulk",
        "fingerprint_hash": "fp_stress_393304cecc784f219fc20ac7c9ae1491",
        "created_at": "2026-03-25T16:59:09.062446+00:00"
      },
      {
        "id": "45a82c21-7bb0-4125-8db7-2ed43f2ceae8",
        "request_id": "f4b464c9-704f-4c93-9984-65f5eb4e5bc0",
        "visitor_id": "stress-1774457938570",
        "modelo_id": "MODEL_ID_PLACEHOLDER",
        "boton_clickado": "onlyfans",
        "utm_source": "stress",
        "idioma": "es",
        "dispositivo": "mobile",
        "user_agent": "stress-bulk",
        "fingerprint_hash": "fp_stress_393304cecc784f219fc20ac7c9ae1491",
        "created_at": "2026-03-25T16:59:09.431362+00:00"
      },
      {
        "id": "1249be86-bbdc-4801-986c-d90383f8cb49",
        "request_id": "18479369-cbbc-49c1-9622-a0942409f1c3",
        "visitor_id": "stress-1774457938570",
        "modelo_id": "MODEL_ID_PLACEHOLDER",
        "boton_clickado": "telegram",
        "utm_source": "stress",
        "idioma": "es",
        "dispositivo": "mobile",
        "user_agent": "stress-bulk",
        "fingerprint_hash": "fp_stress_393304cecc784f219fc20ac7c9ae1491",
        "created_at": "2026-03-25T16:59:09.878672+00:00"
      },
      {
        "id": "182aae63-7698-43d7-b25b-f1ddc303b47d",
        "request_id": "4fc41b3e-f59c-407f-abe1-6ee27ec850aa",
        "visitor_id": "stress-1774457938570",
        "modelo_id": "MODEL_ID_PLACEHOLDER",
        "boton_clickado": "onlyfans",
        "utm_source": "stress",
        "idioma": "es",
        "dispositivo": "mobile",
        "user_agent": "stress-bulk",
        "fingerprint_hash": "fp_stress_393304cecc784f219fc20ac7c9ae1491",
        "created_at": "2026-03-25T16:59:10.186095+00:00"
      },
      {
        "id": "bcda3663-ab2d-4501-8108-29651bd2f275",
        "request_id": "e8e7eab5-9f6f-4dd7-b85f-680fc3e0b140",
        "visitor_id": "stress-1774457938570",
        "modelo_id": "MODEL_ID_PLACEHOLDER",
        "boton_clickado": "telegram",
        "utm_source": "stress",
        "idioma": "es",
        "dispositivo": "mobile",
        "user_agent": "stress-bulk",
        "fingerprint_hash": "fp_stress_393304cecc784f219fc20ac7c9ae1491",
        "created_at": "2026-03-25T16:59:10.512488+00:00"
      },
      {
        "id": "c7dd6cc3-29df-4244-88a7-45d521e9acc7",
        "request_id": "3fb0f232-3019-4512-9ebd-674ba33f8bc5",
        "visitor_id": "stress-1774457938570",
        "modelo_id": "MODEL_ID_PLACEHOLDER",
        "boton_clickado": "onlyfans",
        "utm_source": "stress",
        "idioma": "es",
        "dispositivo": "mobile",
        "user_agent": "stress-bulk",
        "fingerprint_hash": "fp_stress_393304cecc784f219fc20ac7c9ae1491",
        "created_at": "2026-03-25T16:59:10.882165+00:00"
      },
      {
        "id": "59be95fd-ede2-40e8-9346-3981260142e7",
        "request_id": "83898195-a446-428b-a91f-8daf5a707edf",
        "visitor_id": "stress-1774457938570",
        "modelo_id": "MODEL_ID_PLACEHOLDER",
        "boton_clickado": "telegram",
        "utm_source": "stress",
        "idioma": "es",
        "dispositivo": "mobile",
        "user_agent": "stress-bulk",
        "fingerprint_hash": "fp_stress_393304cecc784f219fc20ac7c9ae1491",
        "created_at": "2026-03-25T16:59:11.237501+00:00"
      },
      {
        "id": "df1fc9d3-c95f-4b8b-8747-06e666d9f288",
        "request_id": "c897ede4-0e4d-44fe-92ed-bb6795353048",
        "visitor_id": "feec137e-5b4d-4247-acd7-7331fda6de2c",
        "modelo_id": "MODEL_ID_PLACEHOLDER",
        "boton_clickado": "telegram",
        "utm_source": "instagram",
        "idioma": "es",
        "dispositivo": "mobile",
        "user_agent": "audit-script",
        "fingerprint_hash": "audit_fp_d6552ea580504fc59474db2aab0ce412",
        "created_at": "2026-03-25T17:02:22.536696+00:00"
      },
      {
        "id": "ffdc9b92-840b-4409-a3c5-57f229d915d0",
        "request_id": "c6726757-37d2-4abe-8f96-1e375f6600b2",
        "visitor_id": "feec137e-5b4d-4247-acd7-7331fda6de2c",
        "modelo_id": "MODEL_ID_PLACEHOLDER",
        "boton_clickado": "onlyfans",
        "utm_source": "instagram",
        "idioma": "es",
        "dispositivo": "mobile",
        "user_agent": "audit-script",
        "fingerprint_hash": "audit_fp_d6552ea580504fc59474db2aab0ce412",
        "created_at": "2026-03-25T17:02:23.901725+00:00"
      },
      {
        "id": "86a2281c-d12a-4f54-8202-d038fcd6904a",
        "request_id": "4307cc88-790a-4e1f-b9ad-d208baeab874",
        "visitor_id": "91c31bf1-c7ff-4d66-a1ca-c2f574947f3a",
        "modelo_id": "MODEL_ID_PLACEHOLDER",
        "boton_clickado": "telegram",
        "utm_source": "edge",
        "idioma": "es",
        "dispositivo": "mobile",
        "user_agent": "audit-edge",
        "fingerprint_hash": "dup_3c251b8cb1324009b0a16951c660d451",
        "created_at": "2026-03-25T17:02:25.305629+00:00"
      },
      {
        "id": "bf5b225a-6a27-4af7-ae16-458d54d72238",
        "request_id": "b971a305-9b87-480d-b094-dc35e3e6a267",
        "visitor_id": "9aeec2a6-45be-4dba-89e8-9202926a2fc0",
        "modelo_id": "MODEL_ID_PLACEHOLDER",
        "boton_clickado": "telegram",
        "utm_source": "instagram",
        "idioma": "es",
        "dispositivo": "mobile",
        "user_agent": "audit-script",
        "fingerprint_hash": "audit_fp_f2163754d2ff44e88d531543d66755c2",
        "created_at": "2026-03-25T17:03:09.805148+00:00"
      },
      {
        "id": "3344d602-c0f1-44f8-a0a5-e31f889d1363",
        "request_id": "86793af6-0453-45dc-b2f7-171cb333b483",
        "visitor_id": "9aeec2a6-45be-4dba-89e8-9202926a2fc0",
        "modelo_id": "MODEL_ID_PLACEHOLDER",
        "boton_clickado": "onlyfans",
        "utm_source": "instagram",
        "idioma": "es",
        "dispositivo": "mobile",
        "user_agent": "audit-script",
        "fingerprint_hash": "audit_fp_f2163754d2ff44e88d531543d66755c2",
        "created_at": "2026-03-25T17:03:11.015283+00:00"
      },
      {
        "id": "b35cb27f-5fa6-40c2-9a8f-3834c53a8c55",
        "request_id": "9efcfade-ae71-4a9f-8003-718b612aee5e",
        "visitor_id": "983222f1-06bc-470c-ba9a-3a5ce2142d44",
        "modelo_id": "MODEL_ID_PLACEHOLDER",
        "boton_clickado": "telegram",
        "utm_source": "edge",
        "idioma": "es",
        "dispositivo": "mobile",
        "user_agent": "audit-edge",
        "fingerprint_hash": "dup_6f62ebbf1cb147ecb35bdc4a6b9087d4",
        "created_at": "2026-03-25T17:03:12.422638+00:00"
      },
      {
        "id": "13334df7-4e3f-4511-b348-87ecff01676a",
        "request_id": "d3ae1b07-7f5c-46b8-b861-743649499bf1",
        "visitor_id": "24bcbb59-d22b-4b26-820f-03140c22c12c",
        "modelo_id": "MODEL_ID_PLACEHOLDER",
        "boton_clickado": "telegram",
        "utm_source": "smoke",
        "idioma": "es",
        "dispositivo": "mobile",
        "user_agent": "smoke-daily",
        "fingerprint_hash": "smoke_fp_62508e2efdcf44879ae80b982deb0242",
        "created_at": "2026-03-25T18:04:07.53524+00:00"
      },
      {
        "id": "6288c5ff-19e4-4ff1-ad46-22d307392056",
        "request_id": "ce6f6252-a95f-43af-9322-24491c94ef9b",
        "visitor_id": "test-batch-1774477751727-f1-user",
        "modelo_id": "MODEL_ID_PLACEHOLDER",
        "boton_clickado": "telegram",
        "utm_source": "tiktok",
        "idioma": "es",
        "dispositivo": "mobile",
        "user_agent": "f1-test",
        "fingerprint_hash": "fp_test-batch-1774477751727_deviceA",
        "created_at": "2026-03-25T22:29:13.577162+00:00"
      },
      {
        "id": "9400cd38-7795-4081-bdc6-4550d1a7f1f5",
        "request_id": "fdb3429a-12c0-4114-9e17-72a5d4e1a104",
        "visitor_id": "test-batch-1774477751727-f1-user",
        "modelo_id": "MODEL_ID_PLACEHOLDER",
        "boton_clickado": "onlyfans",
        "utm_source": "tiktok",
        "idioma": "es",
        "dispositivo": "mobile",
        "user_agent": "f1-test",
        "fingerprint_hash": "fp_test-batch-1774477751727_deviceA",
        "created_at": "2026-03-25T22:29:14.262735+00:00"
      },
      {
        "id": "511ba81b-265d-4494-b9b0-58f60841ae46",
        "request_id": "d394a80d-fdb1-4ff4-9c81-61c09f969105",
        "visitor_id": "test-batch-1774477751727-f25",
        "modelo_id": "MODEL_ID_PLACEHOLDER",
        "boton_clickado": "telegram",
        "utm_source": "reddit",
        "idioma": "es",
        "dispositivo": "mobile",
        "user_agent": "f25-test",
        "fingerprint_hash": "fp_test-batch-1774477751727_f25",
        "created_at": "2026-03-25T22:29:21.022389+00:00"
      },
      {
        "id": "2aea3ac2-8b1f-4d06-a421-7eaeb772e8f4",
        "request_id": "34d70ef1-a26d-4ada-aa5e-d3c0064e6142",
        "visitor_id": "test-f25-final-1774477992089",
        "modelo_id": "MODEL_ID_PLACEHOLDER",
        "boton_clickado": "telegram",
        "utm_source": "reddit",
        "idioma": "es",
        "dispositivo": "mobile",
        "user_agent": "f25-final",
        "fingerprint_hash": "fp_test-f25-final-1774477992089",
        "created_at": "2026-03-25T22:33:14.913099+00:00"
      },
      {
        "id": "280fc75e-7591-4f71-b342-c29485e702e5",
        "request_id": "442ec753-cba6-4baa-a2e5-638972317e47",
        "visitor_id": "488bb783-7c28-442b-a508-5be8db15733a",
        "modelo_id": "MODEL_ID_PLACEHOLDER",
        "boton_clickado": "telegram",
        "utm_source": "smoke",
        "idioma": "es",
        "dispositivo": "mobile",
        "user_agent": "smoke-daily",
        "fingerprint_hash": "smoke_fp_53ff84257409458d9309c7cd39508da0",
        "created_at": "2026-03-25T22:38:57.910243+00:00"
      },
      {
        "id": "afb3360b-600c-432d-8bc6-f2038eceb268",
        "request_id": "3efff832-6004-4ed8-ab00-1e211a65bfb3",
        "visitor_id": "test-f25-final-1774478688926",
        "modelo_id": "MODEL_ID_PLACEHOLDER",
        "boton_clickado": "telegram",
        "utm_source": "reddit",
        "idioma": "es",
        "dispositivo": "mobile",
        "user_agent": "f25-final",
        "fingerprint_hash": "fp_test-f25-final-1774478688926",
        "created_at": "2026-03-25T22:44:51.115021+00:00"
      },
      {
        "id": "416e8eba-ba32-4fd4-b4f0-e8da1e683ee6",
        "request_id": "04bd8c80-0aaa-436e-91c6-dd3f40d1873a",
        "visitor_id": "e34085df-6b9f-401c-8513-d601ff85ecc3",
        "modelo_id": "MODEL_ID_PLACEHOLDER",
        "boton_clickado": "telegram",
        "utm_source": "smoke",
        "idioma": "es",
        "dispositivo": "mobile",
        "user_agent": "smoke-daily",
        "fingerprint_hash": "smoke_fp_984f5a982ef64a03a08c2a26a57bd574",
        "created_at": "2026-03-25T22:45:03.783696+00:00"
      },
      {
        "id": "f1d576bd-0d16-446d-937d-e3e3d76f7194",
        "request_id": "586ebf61-b979-4310-9e0c-7527e7d037a2",
        "visitor_id": "test-batch-1774478704617-f1-user",
        "modelo_id": "MODEL_ID_PLACEHOLDER",
        "boton_clickado": "telegram",
        "utm_source": "tiktok",
        "idioma": "es",
        "dispositivo": "mobile",
        "user_agent": "f1-test",
        "fingerprint_hash": "fp_test-batch-1774478704617_deviceA",
        "created_at": "2026-03-25T22:45:05.900182+00:00"
      },
      {
        "id": "e4a3c49f-fc48-4930-be74-7e7743a386e0",
        "request_id": "b76ab8e7-5495-4f37-ad6b-7d8f2cbe449a",
        "visitor_id": "test-batch-1774478704617-f1-user",
        "modelo_id": "MODEL_ID_PLACEHOLDER",
        "boton_clickado": "onlyfans",
        "utm_source": "tiktok",
        "idioma": "es",
        "dispositivo": "mobile",
        "user_agent": "f1-test",
        "fingerprint_hash": "fp_test-batch-1774478704617_deviceA",
        "created_at": "2026-03-25T22:45:06.498613+00:00"
      },
      {
        "id": "d4043bdc-f318-40b5-9341-bb727193beba",
        "request_id": "372aba87-8e1f-44ce-8da8-8d70129a4361",
        "visitor_id": "856a3c5a-5870-4a0c-a417-a693e52e675f",
        "modelo_id": "MODEL_ID_PLACEHOLDER",
        "boton_clickado": "telegram",
        "utm_source": "smoke",
        "idioma": "es",
        "dispositivo": "mobile",
        "user_agent": "smoke-daily",
        "fingerprint_hash": "smoke_fp_5422491691144d38ad40bc960a2dd1b9",
        "created_at": "2026-03-25T22:50:25.399521+00:00"
      },
      {
        "id": "e53c6224-52e7-404d-a422-c41865d39551",
        "request_id": "a1d2b43c-823d-445a-96a4-7892a21963de",
        "visitor_id": "test-f25-final-1774479035615",
        "modelo_id": "MODEL_ID_PLACEHOLDER",
        "boton_clickado": "telegram",
        "utm_source": "reddit",
        "idioma": "es",
        "dispositivo": "mobile",
        "user_agent": "f25-final",
        "fingerprint_hash": "fp_test-f25-final-1774479035615",
        "created_at": "2026-03-25T22:50:37.459273+00:00"
      },
      {
        "id": "d49447c5-efd1-43ad-90a8-67fd89f90f28",
        "request_id": "69168072-eee2-4f40-8f69-bc74f9cdeda7",
        "visitor_id": "35f9f7e6-5c57-46c6-a205-c0e8e0f11e2d",
        "modelo_id": "MODEL_ID_PLACEHOLDER",
        "boton_clickado": "telegram",
        "utm_source": "smoke",
        "idioma": "es",
        "dispositivo": "mobile",
        "user_agent": "smoke-daily",
        "fingerprint_hash": "smoke_fp_1f32a8fcecc442368223d5aafbafdef1",
        "created_at": "2026-03-25T23:10:40.785755+00:00"
      },
      {
        "id": "5d18d23f-3c73-493c-966a-049445ea76d5",
        "request_id": "64286938-59d2-4859-850b-75c22bceb6df",
        "visitor_id": "531c55fd-49af-48fe-9df4-64bbd349369e",
        "modelo_id": "MODEL_ID_PLACEHOLDER",
        "boton_clickado": "telegram",
        "utm_source": "smoke",
        "idioma": "es",
        "dispositivo": "mobile",
        "user_agent": "smoke-daily",
        "fingerprint_hash": "smoke_fp_f305fc492bfc443087826046ac0feca0",
        "created_at": "2026-03-25T23:11:21.351476+00:00"
      },
      {
        "id": "aee281ce-c77a-42f6-9f8d-0285e9430dd7",
        "request_id": "a121fe86-abe9-49fc-bf1a-0f790f4e7509",
        "visitor_id": "545e6caf-52b2-4de8-9933-062bb5f5c506",
        "modelo_id": "MODEL_ID_PLACEHOLDER",
        "boton_clickado": "telegram",
        "utm_source": "smoke",
        "idioma": "es",
        "dispositivo": "mobile",
        "user_agent": "smoke-daily",
        "fingerprint_hash": "smoke_fp_43b016ca67ff4f1896ea0242110bc008",
        "created_at": "2026-03-25T23:14:14.13458+00:00"
      }
    ]
  }
}